fastpdb-1.3.3.dist-info/METADATA
fastpdb-1.3.3.dist-info/WHEEL
fastpdb-1.3.3.dist-info/licenses/LICENSE
fastpdb/__init__.py
fastpdb/fastpdb.cpython-310-darwin.so
fastpdb-1.3.3.dist-info/RECORD
