Metadata-Version: 2.4
Name: fastpdb
Version: 1.3.3
Classifier: Development Status :: 5 - Production/Stable
Classifier: Intended Audience :: Science/Research
Classifier: License :: OSI Approved :: BSD License
Classifier: Natural Language :: English
Classifier: Operating System :: POSIX :: Linux
Classifier: Operating System :: MacOS
Classifier: Operating System :: Microsoft :: Windows
Classifier: Programming Language :: Python :: 3
Classifier: Topic :: Scientific/Engineering :: Bio-Informatics
Requires-Dist: biotite >=0.39
Requires-Dist: pytest ; extra == 'test'
Requires-Dist: pytest-codspeed ; extra == 'test'
Requires-Dist: matplotlib ; extra == 'plot'
Provides-Extra: test
Provides-Extra: plot
License-File: LICENSE
Summary: A high performance drop-in replacement for Biotite's PDBFile.
Keywords: pdb-files
Author: Patrick Kunzmann, Nick Coish
Maintainer: Patrick Kunzmann
Requires-Python: >=3.7
Project-URL: homepage, https://github.com/biotite-dev/fastpdb
Project-URL: repository, https://github.com/biotite-dev/fastpdb
